my_package_pypi_oleksii_vers1/__init__.py
my_package_pypi_oleksii_vers1/your_code.py
my_package_pypi_oleksii_vers1-0.2.0.dist-info/METADATA
my_package_pypi_oleksii_vers1-0.2.0.dist-info/WHEEL
my_package_pypi_oleksii_vers1-0.2.0.dist-info/RECORD
