Metadata-Version: 2.4
Name: my_package_pypi_oleksii_vers1
Version: 0.2.0
Summary: my_package_pypi_oleksii_vers1
Author-email: Oleksii Saiun <oleksiisaiun@example.com>
Requires-Python: >=3.10
